cdk_cloudformation_cyral_sidecar_deployment_module/__init__.py
cdk_cloudformation_cyral_sidecar_deployment_module/py.typed
cdk_cloudformation_cyral_sidecar_deployment_module/_jsii/__init__.py
cdk_cloudformation_cyral_sidecar_deployment_module/_jsii/cyral-sidecar-deployment-module@1.3.0-alpha.7.jsii.tgz
cdk_cloudformation_cyral_sidecar_deployment_module-1.3.0a7.dist-info/LICENSE
cdk_cloudformation_cyral_sidecar_deployment_module-1.3.0a7.dist-info/METADATA
cdk_cloudformation_cyral_sidecar_deployment_module-1.3.0a7.dist-info/WHEEL
cdk_cloudformation_cyral_sidecar_deployment_module-1.3.0a7.dist-info/top_level.txt
cdk_cloudformation_cyral_sidecar_deployment_module-1.3.0a7.dist-info/RECORD
