Metadata-Version: 2.1
Name: cdk-cloudformation-cyral-sidecar-deployment-module
Version: 1.3.0a7
Summary: Schema for Module Fragment of type Cyral::Sidecar::Deployment::MODULE
Home-page: https://github.com/cdklabs/cdk-cloudformation.git
Author: Amazon Web Services
License: Apache-2.0
Project-URL: Source, https://github.com/cdklabs/cdk-cloudformation.git
Classifier: Intended Audience :: Developers
Classifier: Operating System :: OS Independent
Classifier: Programming Language :: JavaScript
Classifier: Programming Language :: Python :: 3 :: Only
Classifier: Programming Language :: Python :: 3.7
Classifier: Programming Language :: Python :: 3.8
Classifier: Programming Language :: Python :: 3.9
Classifier: Programming Language :: Python :: 3.10
Classifier: Programming Language :: Python :: 3.11
Classifier: Typing :: Typed
Classifier: License :: OSI Approved
Requires-Python: ~=3.7
License-File: LICENSE
Requires-Dist: aws-cdk-lib <3.0.0,>=2.99.1
Requires-Dist: constructs <11.0.0,>=10.2.70
Requires-Dist: jsii <2.0.0,>=1.89.0
Requires-Dist: publication >=0.0.3
Requires-Dist: typeguard ~=2.13.3
